{
  "name": "security",
  "description": "Preview & Experimental: Security review, planning, incident response, and risk assessment. Unstable; may change or be removed without notice. Feedback: github.com/microsoft/hve-core/issues",
  "version": "3.3.101",
  "agents": [
    "agents/hve-core/subagents/",
    "agents/rai-planning/",
    "agents/security/",
    "agents/security/subagents/"
  ],
  "commands": [
    "commands/rai-planning/",
    "commands/security/"
  ],
  "skills": [
    "skills/security/",
    "skills/shared/"
  ]
}